bemplt/__init__.py
bemplt/ecg_plot.py
bemplt-0.0.7.dist-info/LICENCE
bemplt-0.0.7.dist-info/METADATA
bemplt-0.0.7.dist-info/WHEEL
bemplt-0.0.7.dist-info/top_level.txt
bemplt-0.0.7.dist-info/RECORD
