Metadata-Version: 2.1
Name: bemplt
Version: 0.0.7
Summary: Plot standard ECG chart from data
Home-page: https://github.com/GaetanDesrues/ecg_plot
Author: dy1901
Author-email: gaetan.desrues@inria.fr
License: MIT License
Platform: UNKNOWN
Classifier: Programming Language :: Python :: 3
Classifier: License :: OSI Approved :: MIT License
Classifier: Operating System :: OS Independent
License-File: LICENCE
